tcpbroker/__init__.py
tcpbroker/__main__.py
tcpbroker/config.py
tcpbroker/utils.py
tcpbroker/cmd/__init__.py
tcpbroker/cmd/control.py
tcpbroker/cmd/easy_setup.py
tcpbroker/cmd/portal.py
tcpbroker/common/IMUParser.py
tcpbroker/common/__init__.py
tcpbroker/common/render.py
tcpbroker/common/repo.py
tcpbroker/common/tcp.py
tcpbroker/functional/__init__.py
tcpbroker/functional/align.py
tcpbroker/functional/convert.py
tcpbroker/functional/ellipse.py
tcpbroker/functional/vector.py
tcpbroker/scripts/__init__.py
tcpbroker/scripts/cli.py
tcpbroker/scripts/configure.py
tcpbroker/tasks/__init__.py
tcpbroker/tasks/imu_render_ui.py
tcpbroker/tasks/measure.py
tcpbroker/tasks/tcp_listen.py
tcpbroker/tasks/tcp_process.py
markit_tcpbroker-1.8.4.dist-info/METADATA
markit_tcpbroker-1.8.4.dist-info/WHEEL
markit_tcpbroker-1.8.4.dist-info/top_level.txt
markit_tcpbroker-1.8.4.dist-info/RECORD
